setup.py
nutritionix/__init__.py
nutritionix/nutritionix.py
nutritionix_client.egg-info/PKG-INFO
nutritionix_client.egg-info/SOURCES.txt
nutritionix_client.egg-info/dependency_links.txt
nutritionix_client.egg-info/requires.txt
nutritionix_client.egg-info/top_level.txt