Metadata-Version: 1.1
Name: nutritionix-client
Version: 1.0.0.dev1
Summary: Official Nutritionix Python Client
Home-page: https://github.com/nutritionix/library-python
Author: Nutritionix
Author-email: info@nutritionix.com
License: MIT
Keywords: nutritionix food nutrition usda
Platform: UNKNOWN
Classifier: Development Status :: 4 - Beta
Classifier: Intended Audience :: Developers
Classifier: Topic :: Software Development :: Build Tools
Classifier: License :: OSI Approved :: MIT License
Classifier: Programming Language :: Python :: 2
Classifier: Programming Language :: Python :: 2.6
Classifier: Programming Language :: Python :: 2.7
Classifier: Programming Language :: Python :: 3
Classifier: Programming Language :: Python :: 3.2
Classifier: Programming Language :: Python :: 3.3
Classifier: Programming Language :: Python :: 3.4
